{
  "centers": [
    {
      "center_id": 694938,
      "name": "Subhash School Burhanpur",
      "address": "Subhash School Shanwara Burhanpur",
      "state_name": "Madhya Pradesh",
      "district_name": "Burhanpur",
      "block_name": "BURHANPUR",
      "pincode": 450331,
      "lat": 21,
      "long": 76,
      "from": "09:00:00",
      "to": "17:00:00",
      "fee_type": "Free",
      "sessions": [
        {
          "session_id": "c843a7e0-2b29-47d4-b5a2-7a0ae4791735",
          "date": "29-05-2021",
          "available_capacity": 0,
          "min_age_limit": 45,
          "vaccine": "COVISHIELD",
          "slots": [
            "09:00AM-11:00AM",
            "11:00AM-01:00PM",
            "01:00PM-03:00PM",
            "03:00PM-05:00PM"
          ],
          "available_capacity_dose1": 0,
          "available_capacity_dose2": 0
        },
        {
          "session_id": "3c174ed7-c8bb-4ca6-bd43-a361e500f002",
          "date": "29-05-2021",
          "available_capacity": 0,
          "min_age_limit": 18,
          "vaccine": "COVISHIELD",
          "slots": [
            "09:00AM-11:00AM",
            "11:00AM-01:00PM",
            "01:00PM-03:00PM",
            "03:00PM-05:00PM"
          ],
          "available_capacity_dose1": 1,
          "available_capacity_dose2": 0
        }
      ]
    },
    {
      "center_id": 671013,
      "name": "Matru Seva Sadan Hospital",
      "address": "Matru Seva Sadan Hospital",
      "state_name": "Madhya Pradesh",
      "district_name": "Burhanpur",
      "block_name": "BURHANPUR",
      "pincode": 450331,
      "lat": 21,
      "long": 21,
      "from": "09:00:00",
      "to": "17:00:00",
      "fee_type": "Free",
      "sessions": [
        {
          "session_id": "659c02a7-944f-40d0-aef9-567cf673b679",
          "date": "29-05-2021",
          "available_capacity": 0,
          "min_age_limit": 45,
          "vaccine": "COVISHIELD",
          "slots": [
            "09:00AM-11:00AM",
            "11:00AM-01:00PM",
            "01:00PM-03:00PM",
            "03:00PM-05:00PM"
          ],
          "available_capacity_dose1": 0,
          "available_capacity_dose2": 0
        },
        {
          "session_id": "14b1ffdf-5447-4d39-9c4f-c64cb280593f",
          "date": "29-05-2021",
          "available_capacity": 0,
          "min_age_limit": 45,
          "vaccine": "COVAXIN",
          "slots": [
            "09:00AM-11:00AM",
            "11:00AM-01:00PM",
            "01:00PM-03:00PM",
            "03:00PM-05:00PM"
          ],
          "available_capacity_dose1": 1,
          "available_capacity_dose2": 0
        }
      ]
    }
  ]
}
